dratio/__init__.py
dratio/client.py
dratio/exceptions.py
dratio/io.py
dratio/utils.py
dratio/models/__init__.py
dratio/models/base.py
dratio/models/dataset.py
dratio/models/dataset_file.py
dratio/models/dataset_version.py
dratio/models/feature.py
dratio/models/license.py
dratio/models/mixins.py
dratio/models/publisher.py
dratio/models/tags.py
dratio/provider/__init__.py
dratio/provider/file_upload.py
dratio/provider/helper_dataset.py
dratio/provider/provider_utils.py
dratio-0.0.16.dist-info/LICENSE
dratio-0.0.16.dist-info/METADATA
dratio-0.0.16.dist-info/WHEEL
dratio-0.0.16.dist-info/top_level.txt
dratio-0.0.16.dist-info/RECORD
