Metadata-Version: 2.1
Name: dratio
Version: 0.0.16
Summary: Python client library for dratio.io API Web services
Author-email: "dratio.io" <info@dratio.io>
Maintainer-email: "dratio.io" <info@dratio.io>
License: Apache-2.0
Project-URL: homepage, https://dratio.io
Project-URL: repository, https://github.com/dratio-io/dratio-python
Project-URL: documentation, https://dratio.readthedocs.io/
Keywords: dratio,API,client,data,web services,pandas,geopandas,data analysis,geospatial,demographics,marketing,income,consumption,GIS
Classifier: Development Status :: 4 - Beta
Classifier: Intended Audience :: Developers
Classifier: Intended Audience :: Science/Research
Classifier: License :: OSI Approved :: Apache Software License
Classifier: Natural Language :: English
Classifier: Operating System :: OS Independent
Classifier: Programming Language :: Python :: 3.7
Classifier: Programming Language :: Python :: 3.8
Classifier: Programming Language :: Python :: 3.9
Classifier: Programming Language :: Python :: 3.10
Classifier: Programming Language :: Python :: 3.11
Classifier: Topic :: Internet :: WWW/HTTP
Classifier: Topic :: Scientific/Engineering
Classifier: Topic :: Scientific/Engineering :: Artificial Intelligence
Classifier: Topic :: Scientific/Engineering :: Information Analysis
Classifier: Topic :: Scientific/Engineering :: GIS
Classifier: Topic :: Sociology
Classifier: Topic :: Software Development :: Libraries :: Python Modules
Classifier: Typing :: Typed
Requires-Python: >=3.7
License-File: LICENSE
Requires-Dist: requests
Requires-Dist: pandas >=0.21.1
Requires-Dist: pyarrow
Requires-Dist: typing-extensions ; python_version < "3.8"
Provides-Extra: docs
Requires-Dist: sphinx ; extra == 'docs'
Requires-Dist: pydata-sphinx-theme ; extra == 'docs'
Provides-Extra: geo
Requires-Dist: geopandas >=0.8 ; extra == 'geo'
